esp_idf_monitor/__init__.py
esp_idf_monitor/__main__.py
esp_idf_monitor/config.py
esp_idf_monitor/idf_monitor.py
esp_idf_monitor/base/__init__.py
esp_idf_monitor/base/ansi_color_converter.py
esp_idf_monitor/base/argument_parser.py
esp_idf_monitor/base/binlog.py
esp_idf_monitor/base/chip_specific_config.py
esp_idf_monitor/base/console_parser.py
esp_idf_monitor/base/console_reader.py
esp_idf_monitor/base/constants.py
esp_idf_monitor/base/coredump.py
esp_idf_monitor/base/exceptions.py
esp_idf_monitor/base/gdbhelper.py
esp_idf_monitor/base/key_config.py
esp_idf_monitor/base/line_matcher.py
esp_idf_monitor/base/logger.py
esp_idf_monitor/base/output_helpers.py
esp_idf_monitor/base/reset.py
esp_idf_monitor/base/rom_elf_getter.py
esp_idf_monitor/base/serial_handler.py
esp_idf_monitor/base/serial_reader.py
esp_idf_monitor/base/stoppable_thread.py
esp_idf_monitor/base/web_socket_client.py
esp_idf_monitor-1.7.0.dist-info/licenses/LICENSE
esp_idf_monitor-1.7.0.dist-info/METADATA
esp_idf_monitor-1.7.0.dist-info/WHEEL
esp_idf_monitor-1.7.0.dist-info/top_level.txt
esp_idf_monitor-1.7.0.dist-info/RECORD
