Metadata-Version: 2.4
Name: esp-idf-monitor
Version: 1.7.0
Summary: Serial monitor for esp-idf
Author: Espressif Systems
Project-URL: Homepage, https://github.com/espressif/esp-idf-monitor
Keywords: espressif,embedded,monitor,serial
Classifier: Development Status :: 5 - Production/Stable
Classifier: Intended Audience :: Developers
Classifier: Natural Language :: English
Classifier: Environment :: Console
Classifier: Topic :: Software Development :: Embedded Systems
Classifier: License :: OSI Approved :: Apache Software License
Classifier: Programming Language :: Python :: 3.7
Classifier: Programming Language :: Python :: 3.8
Classifier: Programming Language :: Python :: 3.9
Classifier: Programming Language :: Python :: 3.10
Classifier: Programming Language :: Python :: 3.11
Classifier: Programming Language :: Python :: 3.12
Classifier: Programming Language :: Python :: 3.13
Classifier: Operating System :: POSIX
Classifier: Operating System :: Microsoft :: Windows
Classifier: Operating System :: MacOS :: MacOS X
Requires-Python: >=3.7
License-File: LICENSE
Requires-Dist: pyserial>=3.3
Requires-Dist: esp-coredump~=1.2
Requires-Dist: esp-idf-panic-decoder~=1.4
Requires-Dist: pyelftools
Provides-Extra: dev
Requires-Dist: pre-commit; extra == "dev"
Requires-Dist: czespressif; python_version >= "3.9" and extra == "dev"
Requires-Dist: coverage[toml]; extra == "dev"
Provides-Extra: ide
Requires-Dist: websocket-client; extra == "ide"
Provides-Extra: target-test
Requires-Dist: SimpleWebSocketServer; extra == "target-test"
Requires-Dist: pytest; extra == "target-test"
Requires-Dist: pytest_embedded; extra == "target-test"
Requires-Dist: pytest_embedded_idf; extra == "target-test"
Requires-Dist: pytest_embedded_serial_esp; extra == "target-test"
Requires-Dist: idf_build_apps; extra == "target-test"
Requires-Dist: idf-component-manager; extra == "target-test"
Provides-Extra: host-test
Requires-Dist: pytest; extra == "host-test"
Requires-Dist: pytest-rerunfailures; extra == "host-test"
Requires-Dist: esptool; extra == "host-test"
Dynamic: license-file
